<annotation><folder>Rishikesh</folder><filename>25.jpg</filename><path>D:\Projects\Tata_steel_PPE\image_exraction_script\Data\Rishikesh\25.jpg</path><source><database>Unknown</database></source><size><width>286</width><height>176</height><depth>3</depth></size><segmented>0</segmented><object><name>human</name><pose>Unspecified</pose><truncated>0</truncated><difficult>0</difficult><bndbox><xmin>206</xmin><ymin>91</ymin><xmax>226</xmax><ymax>127</ymax></bndbox></object><object><name>human</name><pose>Unspecified</pose><truncated>0</truncated><difficult>0</difficult><bndbox><xmin>166</xmin><ymin>93</ymin><xmax>186</xmax><ymax>136</ymax></bndbox></object><object><name>leg</name><pose>Unspecified</pose><truncated>0</truncated><difficult>0</difficult><bndbox><xmin>210</xmin><ymin>110</ymin><xmax>217</xmax><ymax>127</ymax></bndbox></object><object><name>leg</name><pose>Unspecified</pose><truncated>0</truncated><difficult>0</difficult><bndbox><xmin>218</xmin><ymin>110</ymin><xmax>227</xmax><ymax>128</ymax></bndbox></object><object><name>novest</name><pose>Unspecified</pose><truncated>0</truncated><difficult>0</difficult><bndbox><xmin>208</xmin><ymin>98</ymin><xmax>221</xmax><ymax>112</ymax></bndbox></object><object><name>novest</name><pose>Unspecified</pose><truncated>0</truncated><difficult>0</difficult><bndbox><xmin>170</xmin><ymin>103</ymin><xmax>183</xmax><ymax>120</ymax></bndbox></object><object><name>helmet</name><pose>Unspecified</pose><truncated>0</truncated><difficult>0</difficult><bndbox><xmin>210</xmin><ymin>92</ymin><xmax>219</xmax><ymax>99</ymax></bndbox></object><object><name>vest</name><pose>Unspecified</pose><truncated>0</truncated><difficult>0</difficult><bndbox><xmin>95</xmin><ymin>104</ymin><xmax>113</xmax><ymax>140</ymax></bndbox></object></annotation>