<annotation><folder>filterredpart</folder><filename>cK_Batch01_Dash_20230420__000000017880.jpg</filename><path>C:\Users\AdityaKakkar\OneDrive - Tata Insights and Quants\Documents\annotations\taggingProject\fireAndSmokeVideos2\filterredpart\cK_Batch01_Dash_20230420__000000017880.jpg</path><source><database>Unknown</database></source><size><width>1280</width><height>720</height><depth>3</depth></size><segmented>0</segmented><object><name>fire</name><pose>Unspecified</pose><truncated>0</truncated><difficult>0</difficult><bndbox><xmin>1026</xmin><ymin>274</ymin><xmax>1051</xmax><ymax>314</ymax></bndbox></object><object><name>smoke</name><pose>Unspecified</pose><truncated>0</truncated><difficult>0</difficult><bndbox><xmin>862</xmin><ymin>2</ymin><xmax>1068</xmax><ymax>203</ymax></bndbox></object><object><name>fire</name><pose>Unspecified</pose><truncated>0</truncated><difficult>0</difficult><bndbox><xmin>936</xmin><ymin>187</ymin><xmax>962</xmax><ymax>204</ymax></bndbox></object><object><name>fire</name><pose>Unspecified</pose><truncated>0</truncated><difficult>0</difficult><bndbox><xmin>762</xmin><ymin>387</ymin><xmax>796</xmax><ymax>413</ymax></bndbox></object><object><name>fire</name><pose>Unspecified</pose><truncated>0</truncated><difficult>0</difficult><bndbox><xmin>759</xmin><ymin>172</ymin><xmax>841</xmax><ymax>280</ymax></bndbox></object><object><name>fire</name><pose>Unspecified</pose><truncated>0</truncated><difficult>0</difficult><bndbox><xmin>1000</xmin><ymin>308</ymin><xmax>1024</xmax><ymax>339</ymax></bndbox></object><object><name>fire</name><pose>Unspecified</pose><truncated>0</truncated><difficult>0</difficult><bndbox><xmin>870</xmin><ymin>15</ymin><xmax>1278</xmax><ymax>213</ymax></bndbox></object><object><name>fire</name><pose>Unspecified</pose><truncated>0</truncated><difficult>0</difficult><bndbox><xmin>749</xmin><ymin>37</ymin><xmax>786</xmax><ymax>143</ymax></bndbox></object><object><name>fire</name><pose>Unspecified</pose><truncated>0</truncated><difficult>0</difficult><bndbox><xmin>1067</xmin><ymin>137</ymin><xmax>1159</xmax><ymax>219</ymax></bndbox></object><object><name>smoke</name><pose>Unspecified</pose><truncated>0</truncated><difficult>0</difficult><bndbox><xmin>453</xmin><ymin>0</ymin><xmax>614</xmax><ymax>194</ymax></bndbox></object></annotation>